{
  "type": "minecraft:crafting_shapeless",
  "ingredients": [
    {
      "item": "theaurorian:auroriancoalblock"
    },
    {
      "item": "theaurorian:aurorianstone"
    },
    {
      "item": "theaurorian:aurorianstone"
    },
    {
      "item": "theaurorian:aurorianstone"
    },
    {
      "item": "theaurorian:aurorianstone"
    },
    {
      "item": "theaurorian:aurorianstone"
    },
    {
      "item": "theaurorian:aurorianstone"
    },
    {
      "item": "theaurorian:aurorianstone"
    },
    {
      "item": "theaurorian:aurorianstone"
    }
  ],
  "result": {
    "item": "theaurorian:umbrastone",
    "count": 18
  }
}